fruitspace/client.py
fruitspace/enums.py
fruitspace/models.py
fruitspace/urls.py
fruitspace/utils.py
fruitspace.py-1.0.2.dist-info/METADATA
fruitspace.py-1.0.2.dist-info/WHEEL
fruitspace.py-1.0.2.dist-info/top_level.txt
fruitspace.py-1.0.2.dist-info/RECORD
